{
  "updated": "2026-06-26T12:59:03.724967+00:00",
  "overall": "All systems operational",
  "overall_ok": true,
  "checks": [
    {
      "name": "Marketing site",
      "url": "https://huloglobal.com/vendure-plugins/",
      "ok": true,
      "status": 200,
      "ms": 539,
      "err": null,
      "uptime_24h": 99.05,
      "uptime_30d": 99.05
    },
    {
      "name": "Legal \u2014 Terms",
      "url": "https://huloglobal.com/legal/terms/",
      "ok": true,
      "status": 200,
      "ms": 473,
      "err": null,
      "uptime_24h": 99.05,
      "uptime_30d": 99.05
    },
    {
      "name": "Legal \u2014 Privacy",
      "url": "https://huloglobal.com/legal/privacy/",
      "ok": true,
      "status": 200,
      "ms": 210,
      "err": null,
      "uptime_24h": 99.05,
      "uptime_30d": 99.05
    },
    {
      "name": "Buy \u2014 Email Tracking",
      "url": "https://elite.charity/licence/buy/vendure-plugin-email-tracking",
      "ok": true,
      "status": 200,
      "ms": 708,
      "err": null,
      "uptime_24h": 98.1,
      "uptime_30d": 98.1
    },
    {
      "name": "Buy \u2014 Geo Block",
      "url": "https://elite.charity/licence/buy/vendure-plugin-geo-block",
      "ok": true,
      "status": 200,
      "ms": 482,
      "err": null,
      "uptime_24h": 98.1,
      "uptime_30d": 98.1
    },
    {
      "name": "Buy \u2014 Visitor Analytics",
      "url": "https://elite.charity/licence/buy/vendure-plugin-visitor-analytics",
      "ok": true,
      "status": 200,
      "ms": 474,
      "err": null,
      "uptime_24h": 98.1,
      "uptime_30d": 98.1
    },
    {
      "name": "Forgot key",
      "url": "https://elite.charity/licence/forgot",
      "ok": true,
      "status": 200,
      "ms": 201,
      "err": null,
      "uptime_24h": 98.1,
      "uptime_30d": 98.1
    },
    {
      "name": "Privacy request",
      "url": "https://elite.charity/licence/privacy",
      "ok": true,
      "status": 200,
      "ms": 478,
      "err": null,
      "uptime_24h": 98.1,
      "uptime_30d": 98.1
    },
    {
      "name": "Geo-block presets",
      "url": "https://elite.charity/geo-block/presets",
      "ok": true,
      "status": 200,
      "ms": 206,
      "err": null,
      "uptime_24h": 98.1,
      "uptime_30d": 98.1
    },
    {
      "name": "Email-track status",
      "url": "https://elite.charity/email-track/status",
      "ok": true,
      "status": 401,
      "ms": 202,
      "err": null,
      "uptime_24h": 98.1,
      "uptime_30d": 98.1
    },
    {
      "name": "Geo-block status",
      "url": "https://elite.charity/geo-block/status",
      "ok": true,
      "status": 401,
      "ms": 194,
      "err": null,
      "uptime_24h": 98.1,
      "uptime_30d": 98.1
    },
    {
      "name": "Visitor status",
      "url": "https://elite.charity/ees/visitors/status",
      "ok": true,
      "status": 401,
      "ms": 207,
      "err": null,
      "uptime_24h": 98.1,
      "uptime_30d": 98.1
    },
    {
      "name": "Revocation list",
      "url": "https://elite.charity/licence/revoked.json",
      "ok": true,
      "status": 200,
      "ms": 197,
      "err": null,
      "uptime_24h": 98.1,
      "uptime_30d": 98.1
    }
  ]
}