{
  "updated": "2026-06-24T19:32:03.684918+00:00",
  "overall": "All systems operational",
  "overall_ok": true,
  "checks": [
    {
      "name": "Marketing site",
      "url": "https://huloglobal.com/vendure-plugins/",
      "ok": true,
      "status": 200,
      "ms": 615,
      "err": null,
      "uptime_24h": 98.33,
      "uptime_30d": 98.33
    },
    {
      "name": "Legal \u2014 Terms",
      "url": "https://huloglobal.com/legal/terms/",
      "ok": true,
      "status": 200,
      "ms": 539,
      "err": null,
      "uptime_24h": 98.33,
      "uptime_30d": 98.33
    },
    {
      "name": "Legal \u2014 Privacy",
      "url": "https://huloglobal.com/legal/privacy/",
      "ok": true,
      "status": 200,
      "ms": 240,
      "err": null,
      "uptime_24h": 98.33,
      "uptime_30d": 98.33
    },
    {
      "name": "Buy \u2014 Email Tracking",
      "url": "https://elite.charity/licence/buy/vendure-plugin-email-tracking",
      "ok": true,
      "status": 200,
      "ms": 981,
      "err": null,
      "uptime_24h": 96.67,
      "uptime_30d": 96.67
    },
    {
      "name": "Buy \u2014 Geo Block",
      "url": "https://elite.charity/licence/buy/vendure-plugin-geo-block",
      "ok": true,
      "status": 200,
      "ms": 551,
      "err": null,
      "uptime_24h": 96.67,
      "uptime_30d": 96.67
    },
    {
      "name": "Buy \u2014 Visitor Analytics",
      "url": "https://elite.charity/licence/buy/vendure-plugin-visitor-analytics",
      "ok": true,
      "status": 200,
      "ms": 525,
      "err": null,
      "uptime_24h": 96.67,
      "uptime_30d": 96.67
    },
    {
      "name": "Forgot key",
      "url": "https://elite.charity/licence/forgot",
      "ok": true,
      "status": 200,
      "ms": 490,
      "err": null,
      "uptime_24h": 96.67,
      "uptime_30d": 96.67
    },
    {
      "name": "Privacy request",
      "url": "https://elite.charity/licence/privacy",
      "ok": true,
      "status": 200,
      "ms": 525,
      "err": null,
      "uptime_24h": 96.67,
      "uptime_30d": 96.67
    },
    {
      "name": "Geo-block presets",
      "url": "https://elite.charity/geo-block/presets",
      "ok": true,
      "status": 200,
      "ms": 232,
      "err": null,
      "uptime_24h": 96.67,
      "uptime_30d": 96.67
    },
    {
      "name": "Email-track status",
      "url": "https://elite.charity/email-track/status",
      "ok": true,
      "status": 401,
      "ms": 490,
      "err": null,
      "uptime_24h": 96.67,
      "uptime_30d": 96.67
    },
    {
      "name": "Geo-block status",
      "url": "https://elite.charity/geo-block/status",
      "ok": true,
      "status": 401,
      "ms": 211,
      "err": null,
      "uptime_24h": 96.67,
      "uptime_30d": 96.67
    },
    {
      "name": "Visitor status",
      "url": "https://elite.charity/ees/visitors/status",
      "ok": true,
      "status": 401,
      "ms": 528,
      "err": null,
      "uptime_24h": 96.67,
      "uptime_30d": 96.67
    },
    {
      "name": "Revocation list",
      "url": "https://elite.charity/licence/revoked.json",
      "ok": true,
      "status": 200,
      "ms": 244,
      "err": null,
      "uptime_24h": 96.67,
      "uptime_30d": 96.67
    }
  ]
}